wudao/__init__.py
wudao/api_request.py
wudao/base_request.py
wudao/utils/__init__.py
wudao/utils/rsa_util.py
wudao/utils/sse_util.py
wudao-1.3.0.dist-info/METADATA
wudao-1.3.0.dist-info/WHEEL
wudao-1.3.0.dist-info/top_level.txt
wudao-1.3.0.dist-info/RECORD
